{
  "generatedAt": "2026-04-14T07:47:08.109538+00:00",
  "artifacts": [
    {
      "path": "data/feeds.json",
      "algorithm": "sha256",
      "value": "bcbd7557b8523b43a98be41f93d1b62361ea5ba3faa563bd27b9e4594a408742",
      "generatedAt": "2026-04-14T07:47:08.109538+00:00"
    },
    {
      "path": "data/feed.xml",
      "algorithm": "sha256",
      "value": "070931b9ff615528f9ce4e1a6b1d249e78636dd2f93b550b4037d08dcf1f1466",
      "generatedAt": "2026-04-14T07:47:08.109538+00:00"
    },
    {
      "path": "data/azure-retirements.ics",
      "algorithm": "sha256",
      "value": "1a51a1e1696e6c5c76d7e5d40cb89d91b26130f7a9a6161345f49fe14702f131",
      "generatedAt": "2026-04-14T07:47:08.109538+00:00"
    }
  ]
}